[
    {
        "code_coverage": 96.0,
        "execution_time": 0.7093117237091064,
        "tool": "Osiris",
        "pc": 360,
        "type": "overflow",
        "opcode": "ADD"
    },
    {
        "code_coverage": 98.7,
        "execution_time": 1.0588135719299316,
        "tool": "Oyente",
        "pc": 388,
        "type": "reentrancy"
    },
    {
        "code_coverage": 96.0,
        "execution_time": 0.7093117237091064,
        "tool": "Osiris",
        "pc": 483,
        "type": "overflow",
        "opcode": "ADD"
    }
]