{
  "src": [ "0x23a91059fdc9579a9fbd0edc5f2ea0bfdb70deb4.sol" ],
  "knowledge": [
    {
      "abs_patch": [
        "Abs_Insert ({mapping(address => uint256)}, {uint256}, 1, 0, 0, 0 @ {mapping(address => uint256)})"
      ],
      "score": 0.125
    },
    {
      "abs_patch": [
        "Abs_Insert ({mapping(address => uint256)}, {mapping(address => uint256)}, 0, 1, 0, 0 @ {mapping(address => uint256)})"
      ],
      "score": 0.125
    },
    {
      "abs_patch": [
        "Abs_Replace ({mapping(address => uint256)}, {mapping(address => uint256)}, 0, 1, 0, 0 @ {mapping(address => uint256)}, {mapping(address => uint256)}, 0, 1, 0, 0 @ {<=} @ {mapping(address => uint256)} @ {>} @ {mapping(address => uint256)})"
      ],
      "score": -0.125
    },
    {
      "abs_patch": [
        "Abs_AtomLst [\nAbs_NR ({mapping(address => uint256)}, {uint256}, 1, 0, 0, 0)\nAbs_NR ({mapping(address => uint256)}, {mapping(address => uint256)}, 0, 1, 0, 0)\nAbs_NR ({}, {}, 1, 0, 0, 0)\n]"
      ],
      "score": 0.11374999999999999
    },
    {
      "abs_patch": [
        "Abs_AtomLst [\nAbs_Move ({mapping(address => uint256)}, {mapping(address => uint256)}, 0, 1, 0, 0)\nAbs_ElseRevert ({mapping(address => uint256)}, {mapping(address => uint256)}, 0, 1, 0, 0)\n]"
      ],
      "score": 0.625
    },
    {
      "abs_patch": [
        "Abs_AtomLst [\nAbs_Move ({mapping(address => uint256)}, {mapping(address => uint256)}, 0, 1, 0, 0)\nAbs_ElseRevert ({mapping(address => uint256)}, {mapping(address => uint256)}, 0, 1, 0, 0)\n]",
        "Abs_Insert ({mapping(address => uint256)}, {uint256}, 1, 0, 0, 0 @ {mapping(address => uint256)})"
      ],
      "score": 0.75
    }
  ]
}