{
    "Reentrancy": [
        {
            "callOffset": 2306,
            "sStoreOffset": 2327
        },
        {
            "callOffset": 2306,
            "sStoreOffset": 2336
        },
        {
            "callOffset": 2306,
            "sStoreOffset": 2345
        },
        {
            "callOffset": 2306,
            "sStoreOffset": 2373
        },
        {
            "callOffset": 2306,
            "sStoreOffset": 2414
        }
    ],
    "IntegerBugs": [
        {
            "offset": 922,
            "category": "add"
        },
        {
            "offset": 1846,
            "category": "add"
        }
    ],
    "UnhandledExceptions": []
}