{
    "patches": [
        {
            "bug_type": "leaking_ether",
            "pc": 27,
            "patch": [
                {
                    "delete": "",
                    "insert": "CALLER PUSH1_0x1 SSTORE",
                    "insert_mode": "after",
                    "constructor": true
                }
            ]
        },
        {
            "bug_type": "leaking_ether",
            "pc": 195,
            "patch": [
                {
                    "delete": "",
                    "insert": "PUSH1_0x1 SLOAD PUSH20_0xffffffffffffffffffffffffffffffffffffffff AND CALLER EQ PUSH_jump_loc_1 JUMPI PUSH1_0x0 DUP1 REVERT JUMPDEST_jump_loc_1",
                    "insert_mode": "before",
                    "constructor": false
                }
            ]
        }
    ],
    "control_flow_graph_recovery_time": 0.014731168746948242,
    "control_flow_graph_recovery": "100%",
    "original_deployment_size": "32 bytes",
    "patched_deployment_size": "36 bytes",
    "original_runtime_size": "253 bytes",
    "patched_runtime_size": "288 bytes",
    "execution_time": 0.26813578605651855
}